muon.py
muon_optimizer-0.1.0.dist-info/licenses/LICENSE
muon_optimizer-0.1.0.dist-info/METADATA
muon_optimizer-0.1.0.dist-info/WHEEL
muon_optimizer-0.1.0.dist-info/top_level.txt
muon_optimizer-0.1.0.dist-info/RECORD
